{
  "fetchedAt": "2026-02-25T20:30:09.411Z",
  "eurUsd": 0.849,
  "prices": {
    "SXR8": {
      "priceUSD": 630.0399780273438,
      "priceEUR": 534.9039413452148,
      "change": "1.29"
    },
    "VWCE": {
      "priceUSD": 150.86000061035156,
      "priceEUR": 128.08014051818847,
      "change": "1.37"
    },
    "BTC": {
      "priceUSD": 68840.328125,
      "priceEUR": 58445.438578124995,
      "change": "7.43"
    },
    "ETH": {
      "priceUSD": 2064.482666015625,
      "priceEUR": 1752.7457834472655,
      "change": "11.41"
    },
    "SGLD": {
      "priceUSD": 501.0400085449219,
      "priceEUR": 425.3829672546387,
      "change": "-0.06"
    },
    "SP500": {
      "value": 6944.91015625,
      "change": "1.57"
    },
    "NASDAQ": {
      "value": 23145.083984375,
      "change": "2.29"
    },
    "GOLD": {
      "value": 5203.7998046875,
      "change": "0.93"
    },
    "IBEX35": {
      "value": 18461,
      "change": "1.49"
    },
    "EUROSTOXX50": {
      "value": 6173.31982421875,
      "change": "0.93"
    },
    "DAX": {
      "value": 25175.939453125,
      "change": "0.74"
    }
  }
}