{
  "fetchedAt": "2026-06-17T16:00:05.108Z",
  "eurUsd": 0.861,
  "prices": {
    "4GLD": {
      "priceUSD": 140.34842780242815,
      "priceEUR": 120.83999633789062,
      "change": "0.14"
    },
    "XEON": {
      "priceUSD": 173.4796716776459,
      "priceEUR": 149.36599731445312,
      "change": "-0.00"
    },
    "EQQQ": {
      "priceUSD": 737.2822157874201,
      "priceEUR": 634.7999877929688,
      "change": "-1.20"
    },
    "ITX": {
      "priceUSD": 65.55168249327409,
      "priceEUR": 56.439998626708984,
      "change": "0.89"
    },
    "BTC": {
      "priceUSD": 65696.96875,
      "priceEUR": 56565.09009375,
      "change": "0.15"
    },
    "SOL": {
      "priceUSD": 73.7699966430664,
      "priceEUR": 63.515967109680176,
      "change": "0.49"
    },
    "SXR8": {
      "priceUSD": 810.7085011977352,
      "priceEUR": 698.02001953125,
      "change": "-0.51"
    },
    "VWCE": {
      "priceUSD": 191.21951148623512,
      "priceEUR": 164.63999938964844,
      "change": "0.02"
    },
    "SAP": {
      "priceUSD": 163.9721169288981,
      "priceEUR": 141.17999267578125,
      "change": "-1.40"
    },
    "ASML": {
      "priceUSD": 1923.809552164997,
      "priceEUR": 1656.4000244140625,
      "change": "4.10"
    },
    "MC": {
      "priceUSD": 593.4959349593496,
      "priceEUR": 511,
      "change": "-1.79"
    },
    "SIE": {
      "priceUSD": 317.1893218391587,
      "priceEUR": 273.1000061035156,
      "change": "1.02"
    },
    "AIR": {
      "priceUSD": 217.2125485162148,
      "priceEUR": 187.02000427246094,
      "change": "0.93"
    },
    "NOVO": {
      "priceUSD": 44.45700145926844,
      "priceEUR": 38.27747825643013,
      "change": "1.87"
    },
    "ALV": {
      "priceUSD": 464.8083765470746,
      "priceEUR": 400.20001220703125,
      "change": "1.39"
    },
    "TTE": {
      "priceUSD": 83.86759475548509,
      "priceEUR": 72.20999908447266,
      "change": "-1.15"
    },
    "DTE": {
      "priceUSD": 31.31242634665814,
      "priceEUR": 26.959999084472656,
      "change": "-3.20"
    },
    "SP500": {
      "value": 7517.93017578125,
      "change": "-0.48"
    },
    "NASDAQ": {
      "value": 26390.5859375,
      "change": "-1.10"
    },
    "GOLD": {
      "value": 4378.7001953125,
      "change": "1.10"
    },
    "IBEX35": {
      "value": 19421.900390625,
      "change": "1.35"
    },
    "EUROSTOXX50": {
      "value": 6300.06982421875,
      "change": "0.68"
    },
    "DAX": {
      "value": 24934.669921875,
      "change": "0.16"
    }
  }
}