{
  "fetchedAt": "2026-05-05T07:00:04.644Z",
  "eurUsd": 0.855,
  "prices": {
    "ETH": {
      "priceUSD": 2378.909912109375,
      "priceEUR": 2033.9679748535157,
      "change": "1.39"
    },
    "4GLD": {
      "priceUSD": 145.75438917728894,
      "priceEUR": 124.62000274658203,
      "change": "-1.65"
    },
    "XEON": {
      "priceUSD": 174.31462159630848,
      "priceEUR": 149.03900146484375,
      "change": "0.01"
    },
    "EQQQ": {
      "priceUSD": 674.6198687637061,
      "priceEUR": 576.7999877929688,
      "change": "1.55"
    },
    "BTC": {
      "priceUSD": 80972.25,
      "priceEUR": 69231.27375,
      "change": "1.43"
    },
    "SOL": {
      "priceUSD": 84.9800033569336,
      "priceEUR": 72.65790287017822,
      "change": "1.06"
    },
    "SXR8": {
      "priceUSD": 773.6140379431653,
      "priceEUR": 661.4400024414062,
      "change": "0.74"
    },
    "VWCE": {
      "priceUSD": 180.7719269691155,
      "priceEUR": 154.55999755859375,
      "change": "0.39"
    },
    "SAP": {
      "priceUSD": 173.16958778782896,
      "priceEUR": 148.05999755859375,
      "change": "1.76"
    },
    "ASML": {
      "priceUSD": 1388.7719583790206,
      "priceEUR": 1187.4000244140625,
      "change": "0.00"
    },
    "MC": {
      "priceUSD": 520.4093710023758,
      "priceEUR": 444.95001220703125,
      "change": "0.00"
    },
    "ITX": {
      "priceUSD": 57.766081157483555,
      "priceEUR": 49.38999938964844,
      "change": "-0.00"
    },
    "SIE": {
      "priceUSD": 291.8713485985472,
      "priceEUR": 249.5500030517578,
      "change": "-1.19"
    },
    "AIR": {
      "priceUSD": 206.05847096582602,
      "priceEUR": 176.17999267578125,
      "change": "-0.00"
    },
    "NOVO": {
      "priceUSD": 44.80033864822916,
      "priceEUR": 38.30428954423593,
      "change": "0.99"
    },
    "ALV": {
      "priceUSD": 441.2865354303728,
      "priceEUR": 377.29998779296875,
      "change": "-3.01"
    },
    "TTE": {
      "priceUSD": 91.98830587822094,
      "priceEUR": 78.6500015258789,
      "change": "0.00"
    },
    "DTE": {
      "priceUSD": 31.590643542551856,
      "priceEUR": 27.010000228881836,
      "change": "-2.03"
    },
    "SP500": {
      "value": 7200.75,
      "change": "-0.11"
    },
    "NASDAQ": {
      "value": 25067.80078125,
      "change": "0.70"
    },
    "GOLD": {
      "value": 4558.2998046875,
      "change": "0.86"
    },
    "IBEX35": {
      "value": 17356.099609375,
      "change": "-0.00"
    },
    "EUROSTOXX50": {
      "value": 5763.60986328125,
      "change": "-0.00"
    },
    "DAX": {
      "value": 23991.26953125,
      "change": "-1.24"
    }
  }
}