{
  "fetchedAt": "2026-05-04T16:00:04.599Z",
  "eurUsd": 0.852,
  "prices": {
    "ETH": {
      "priceUSD": 2349.85009765625,
      "priceEUR": 2002.072283203125,
      "change": "1.22"
    },
    "4GLD": {
      "priceUSD": 146.26760885749064,
      "priceEUR": 124.62000274658203,
      "change": "-0.37"
    },
    "XEON": {
      "priceUSD": 174.92840547516872,
      "priceEUR": 149.03900146484375,
      "change": "0.03"
    },
    "EQQQ": {
      "priceUSD": 676.9952908368178,
      "priceEUR": 576.7999877929688,
      "change": "1.60"
    },
    "BTC": {
      "priceUSD": 80031.0078125,
      "priceEUR": 68186.41865625,
      "change": "1.90"
    },
    "SOL": {
      "priceUSD": 84.4800033569336,
      "priceEUR": 71.97696286010742,
      "change": "0.69"
    },
    "SXR8": {
      "priceUSD": 776.3380310345144,
      "priceEUR": 661.4400024414062,
      "change": "0.92"
    },
    "VWCE": {
      "priceUSD": 181.40844783872507,
      "priceEUR": 154.55999755859375,
      "change": "0.94"
    },
    "SAP": {
      "priceUSD": 173.7793398575044,
      "priceEUR": 148.05999755859375,
      "change": "1.49"
    },
    "ASML": {
      "priceUSD": 1393.662000485989,
      "priceEUR": 1187.4000244140625,
      "change": "-2.86"
    },
    "MC": {
      "priceUSD": 522.2417983650602,
      "priceEUR": 444.95001220703125,
      "change": "-1.43"
    },
    "ITX": {
      "priceUSD": 57.96948285170004,
      "priceEUR": 49.38999938964844,
      "change": "-2.35"
    },
    "SIE": {
      "priceUSD": 292.89906461473925,
      "priceEUR": 249.5500030517578,
      "change": "1.13"
    },
    "AIR": {
      "priceUSD": 206.78402896218458,
      "priceEUR": 176.17999267578125,
      "change": "0.74"
    },
    "NOVO": {
      "priceUSD": 44.51755406094338,
      "priceEUR": 37.92895605992376,
      "change": "1.78"
    },
    "ALV": {
      "priceUSD": 442.840361259353,
      "priceEUR": 377.29998779296875,
      "change": "-1.97"
    },
    "TTE": {
      "priceUSD": 92.31220836370764,
      "priceEUR": 78.6500015258789,
      "change": "-0.81"
    },
    "DTE": {
      "priceUSD": 31.701878202912955,
      "priceEUR": 27.010000228881836,
      "change": "-1.13"
    },
    "SP500": {
      "value": 7198.85009765625,
      "change": "-0.14"
    },
    "NASDAQ": {
      "value": 25014.986328125,
      "change": "0.49"
    },
    "GOLD": {
      "value": 4532.7998046875,
      "change": "-2.40"
    },
    "IBEX35": {
      "value": 17356.099609375,
      "change": "-2.39"
    },
    "EUROSTOXX50": {
      "value": 5763.60986328125,
      "change": "-2.00"
    },
    "DAX": {
      "value": 23991.26953125,
      "change": "0.15"
    }
  }
}