{
  "fetchedAt": "2026-05-15T10:00:06.762Z",
  "eurUsd": 0.856,
  "prices": {
    "ETH": {
      "priceUSD": 2254.070068359375,
      "priceEUR": 1929.483978515625,
      "change": "-1.18"
    },
    "4GLD": {
      "priceUSD": 146.86916030455973,
      "priceEUR": 125.72000122070312,
      "change": "-2.47"
    },
    "XEON": {
      "priceUSD": 174.20560177241532,
      "priceEUR": 149.1199951171875,
      "change": "-0.00"
    },
    "EQQQ": {
      "priceUSD": 715.3037240572065,
      "priceEUR": 612.2999877929688,
      "change": "0.41"
    },
    "BTC": {
      "priceUSD": 80488.0078125,
      "priceEUR": 68897.7346875,
      "change": "-0.69"
    },
    "SOL": {
      "priceUSD": 91.1500015258789,
      "priceEUR": 78.02440130615234,
      "change": "-1.08"
    },
    "SXR8": {
      "priceUSD": 801.8691873996057,
      "priceEUR": 686.4000244140625,
      "change": "0.84"
    },
    "VWCE": {
      "priceUSD": 185.95793536890332,
      "priceEUR": 159.17999267578125,
      "change": "0.03"
    },
    "SAP": {
      "priceUSD": 165.6074702182663,
      "priceEUR": 141.75999450683594,
      "change": "4.04"
    },
    "ASML": {
      "priceUSD": 1523.5980737989194,
      "priceEUR": 1304.199951171875,
      "change": "-4.59"
    },
    "MC": {
      "priceUSD": 532.0093386641173,
      "priceEUR": 455.3999938964844,
      "change": "-1.18"
    },
    "ITX": {
      "priceUSD": 57.35981130154334,
      "priceEUR": 49.099998474121094,
      "change": "-0.32"
    },
    "SIE": {
      "priceUSD": 307.24299065420564,
      "priceEUR": 263,
      "change": "-1.42"
    },
    "AIR": {
      "priceUSD": 197.21963472455462,
      "priceEUR": 168.82000732421875,
      "change": "-2.27"
    },
    "NOVO": {
      "priceUSD": 46.85425261942686,
      "priceEUR": 40.10724024222939,
      "change": "0.91"
    },
    "ALV": {
      "priceUSD": 439.0186773282345,
      "priceEUR": 375.79998779296875,
      "change": "0.94"
    },
    "TTE": {
      "priceUSD": 91.54205678779388,
      "priceEUR": 78.36000061035156,
      "change": "0.10"
    },
    "DTE": {
      "priceUSD": 32.46495434056933,
      "priceEUR": 27.790000915527344,
      "change": "-0.61"
    },
    "SP500": {
      "value": 7501.240234375,
      "change": "1.35"
    },
    "NASDAQ": {
      "value": 26635.220703125,
      "change": "2.10"
    },
    "GOLD": {
      "value": 4539.89990234375,
      "change": "-2.95"
    },
    "IBEX35": {
      "value": 17557,
      "change": "-1.42"
    },
    "EUROSTOXX50": {
      "value": 5828.64013671875,
      "change": "-0.55"
    },
    "DAX": {
      "value": 24036.240234375,
      "change": "-0.42"
    }
  }
}