{
  "generatedAt": "2026-04-10T07:00:19.459Z",
  "balance": 4289.82,
  "totalReturn": -14.2,
  "alerts": [
    {
      "asset": "ETH",
      "type": "STOP_LOSS",
      "currentPrice": 2184.1584,
      "triggerPrice": 1900,
      "currency": "USD",
      "distancePct": 13.01,
      "status": "ACTIVE"
    },
    {
      "asset": "4GLD",
      "type": "STOP_LOSS",
      "currentPrice": 131.75,
      "triggerPrice": 105.88,
      "currency": "EUR",
      "distancePct": 19.64,
      "status": "ACTIVE"
    },
    {
      "type": "PORTFOLIO_DRAWDOWN",
      "pnlPct": -14.2,
      "status": "WARNING",
      "detail": "Portfolio down -14.2% from start"
    }
  ]
}