{
  "generatedAt": "2026-05-26T16:00:07.379Z",
  "balance": 4598.2,
  "totalReturn": -8.04,
  "alerts": [
    {
      "asset": "ETH",
      "type": "STOP_LOSS",
      "currentPrice": 2085.6,
      "triggerPrice": 1900,
      "currency": "USD",
      "distancePct": 8.9,
      "status": "ACTIVE"
    },
    {
      "asset": "4GLD",
      "type": "STOP_LOSS",
      "currentPrice": 124.71,
      "triggerPrice": 105.88,
      "currency": "EUR",
      "distancePct": 15.1,
      "status": "ACTIVE"
    },
    {
      "asset": "EQQQ",
      "type": "STOP_LOSS",
      "currentPrice": 629.9,
      "triggerPrice": 508.7824,
      "currency": "EUR",
      "distancePct": 19.23,
      "status": "ACTIVE"
    }
  ]
}