{
  "date": "2026-07-02",
  "day": 139,
  "balance": {
    "total": 4535.72,
    "currency": "EUR"
  },
  "change": {
    "absolute": 0,
    "percentage": 0
  },
  "totalReturn": -9.29,
  "positions": [
    {
      "asset": "CASH",
      "type": "Cash",
      "value": 224.94,
      "pnlPercent": 0
    },
    {
      "asset": "4GLD",
      "type": "ETC",
      "description": "Xetra-Gold ETC (1g/unit)",
      "units": 3.7704,
      "entryPriceEUR": 124.56,
      "currentPriceEUR": 115.23,
      "value": 434.46,
      "pnlPercent": -7.49,
      "change24h": 1.5421219598167077
    },
    {
      "asset": "XEON",
      "type": "ETF",
      "description": "Lyxor Smart Overnight Return (€STR)",
      "units": 3.0311,
      "entryPriceEUR": 140.5,
      "currentPriceEUR": 149.526,
      "value": 453.23,
      "pnlPercent": 6.42,
      "change24h": 0.006019382411374327
    },
    {
      "asset": "EQQQ",
      "type": "ETF",
      "description": "Invesco NASDAQ-100 UCITS",
      "units": 3.617747,
      "entryPriceEUR": 524.6,
      "currentPriceEUR": 644.9,
      "value": 2333.09,
      "pnlPercent": 22.93,
      "change24h": 0
    },
    {
      "asset": "ITX",
      "type": "Stock",
      "description": "Inditex — Fashion Retail",
      "units": 19.555182,
      "entryPriceEUR": 53.46,
      "currentPriceEUR": 55.74,
      "value": 1090.01,
      "pnlPercent": 4.26,
      "change24h": 0
    }
  ],
  "metadata": {
    "generatedAt": "2026-07-02T07:00:22.252Z",
    "eurUsd": 0.8771929824561404
  }
}