{
  "date": "2026-06-02",
  "day": 109,
  "balance": {
    "total": 4574.33,
    "currency": "EUR"
  },
  "change": {
    "absolute": 0,
    "percentage": 0
  },
  "totalReturn": -8.51,
  "positions": [
    {
      "asset": "CASH",
      "type": "Cash",
      "value": 213.78,
      "pnlPercent": 0
    },
    {
      "asset": "ETH",
      "type": "Crypto",
      "description": "Ethereum",
      "units": 0.658029,
      "entryPriceUSD": 2052.97,
      "currentPriceUSD": 1972.15,
      "value": 1118.73,
      "pnlPercent": -3.94,
      "change24h": -1.5510618597686499
    },
    {
      "asset": "4GLD",
      "type": "ETC",
      "description": "Xetra-Gold ETC (1g/unit)",
      "units": 3.7704,
      "entryPriceEUR": 124.56,
      "currentPriceEUR": 124.95,
      "value": 471.11,
      "pnlPercent": 0.31,
      "change24h": -0.8490715759403215
    },
    {
      "asset": "XEON",
      "type": "ETF",
      "description": "Lyxor Smart Overnight Return (€STR)",
      "units": 3.0311,
      "entryPriceEUR": 140.5,
      "currentPriceEUR": 149.271,
      "value": 452.46,
      "pnlPercent": 6.24,
      "change24h": 0.01206005909429002
    },
    {
      "asset": "EQQQ",
      "type": "ETF",
      "description": "Invesco NASDAQ-100 UCITS",
      "units": 3.617747,
      "entryPriceEUR": 524.6,
      "currentPriceEUR": 640.8,
      "value": 2318.25,
      "pnlPercent": 22.15,
      "change24h": 0.8498583569405064
    }
  ],
  "metadata": {
    "generatedAt": "2026-06-02T10:00:26.299Z",
    "eurUsd": 0.8620689655172414
  }
}