{
  "date": "2026-07-08",
  "day": 145,
  "balance": {
    "total": 4471.65,
    "currency": "EUR"
  },
  "change": {
    "absolute": 0,
    "percentage": 0
  },
  "totalReturn": -10.57,
  "positions": [
    {
      "asset": "CASH",
      "type": "Cash",
      "value": 224.94,
      "pnlPercent": 0
    },
    {
      "asset": "4GLD",
      "type": "ETC",
      "description": "Xetra-Gold ETC (1g/unit)",
      "units": 3.7704,
      "entryPriceEUR": 124.56,
      "currentPriceEUR": 116.63,
      "value": 439.74,
      "pnlPercent": -6.37,
      "change24h": -0.23096663815227564
    },
    {
      "asset": "XEON",
      "type": "ETF",
      "description": "Lyxor Smart Overnight Return (€STR)",
      "units": 3.0311,
      "entryPriceEUR": 140.5,
      "currentPriceEUR": 149.58,
      "value": 453.39,
      "pnlPercent": 6.46,
      "change24h": 0.008023106546855245
    },
    {
      "asset": "EQQQ",
      "type": "ETF",
      "description": "Invesco NASDAQ-100 UCITS",
      "units": 3.617747,
      "entryPriceEUR": 524.6,
      "currentPriceEUR": 621.9,
      "value": 2249.88,
      "pnlPercent": 18.55,
      "change24h": -2.477654069311599
    },
    {
      "asset": "ITX",
      "type": "Stock",
      "description": "Inditex — Fashion Retail",
      "units": 19.555182,
      "entryPriceEUR": 53.46,
      "currentPriceEUR": 56.44,
      "value": 1103.69,
      "pnlPercent": 5.57,
      "change24h": 0.821722043586997
    }
  ],
  "metadata": {
    "generatedAt": "2026-07-08T07:00:27.033Z",
    "eurUsd": 0.8771929824561404
  }
}