{
  "date": "2026-05-21",
  "day": 97,
  "balance": {
    "total": 4571.64,
    "currency": "EUR"
  },
  "change": {
    "absolute": 0,
    "percentage": 0
  },
  "totalReturn": -8.57,
  "positions": [
    {
      "asset": "CASH",
      "type": "Cash",
      "value": 213.78,
      "pnlPercent": 0
    },
    {
      "asset": "ETH",
      "type": "Crypto",
      "description": "Ethereum",
      "units": 0.658029,
      "entryPriceUSD": 2052.97,
      "currentPriceUSD": 2130.43,
      "value": 1208.52,
      "pnlPercent": 3.77,
      "change24h": 0.1620605336290728
    },
    {
      "asset": "4GLD",
      "type": "ETC",
      "description": "Xetra-Gold ETC (1g/unit)",
      "units": 3.7704,
      "entryPriceEUR": 124.56,
      "currentPriceEUR": 125.16,
      "value": 471.9,
      "pnlPercent": 0.48,
      "change24h": 0.2964981168362772
    },
    {
      "asset": "XEON",
      "type": "ETF",
      "description": "Lyxor Smart Overnight Return (€STR)",
      "units": 3.0311,
      "entryPriceEUR": 140.5,
      "currentPriceEUR": 149.173,
      "value": 452.16,
      "pnlPercent": 6.17,
      "change24h": 0.013409049767695073
    },
    {
      "asset": "EQQQ",
      "type": "ETF",
      "description": "Invesco NASDAQ-100 UCITS",
      "units": 3.617747,
      "entryPriceEUR": 524.6,
      "currentPriceEUR": 615.1,
      "value": 2225.28,
      "pnlPercent": 17.25,
      "change24h": 1.6694214876033096
    }
  ],
  "metadata": {
    "generatedAt": "2026-05-21T16:00:06.981Z",
    "eurUsd": 0.8620689655172414
  }
}